altstreamfield/__init__.py
altstreamfield/admin.py
altstreamfield/apps.py
altstreamfield/edit_handlers.py
altstreamfield/fields.py
altstreamfield/models.py
altstreamfield/urls.py
altstreamfield/utils.py
altstreamfield/views.py
altstreamfield/wagtail_hooks.py
altstreamfield/blocks/__init__.py
altstreamfield/blocks/core.py
altstreamfield/blocks/fields.py
altstreamfield/blocks/streamblock.py
altstreamfield/blocks/structblock.py
altstreamfield/static/altstreamfield/altstreamfield.js
altstreamfield/static/altstreamfield/altstreamfield.js.LICENSE.txt
altstreamfield/static/altstreamfield/altstreamfield.js.map
altstreamfield/static/altstreamfield/streamfield.css
altstreamfield/templates/altstreamfield/blocks/blocktest.html
altstreamfield/templates/altstreamfield/widgets/blockinput.html
altstreamfield/tests/__init__.py
altstreamfield/tests/testfields.py
altstreamfield/tests/testutils.py
altstreamfield/tests/testviews.py
altstreamfield/tests/blocks/__init__.py
altstreamfield/tests/blocks/testcore.py
altstreamfield/tests/blocks/testfields.py
altstreamfield/tests/blocks/teststreamblock.py
altstreamfield/tests/blocks/teststructblock.py
tests/__init__.py
tests/test_settings.py
tests/urls.py
wagtail_altstreamfield-0.0.13.dist-info/LICENSE
wagtail_altstreamfield-0.0.13.dist-info/METADATA
wagtail_altstreamfield-0.0.13.dist-info/WHEEL
wagtail_altstreamfield-0.0.13.dist-info/top_level.txt
wagtail_altstreamfield-0.0.13.dist-info/RECORD
