Metadata-Version: 2.1
Name: wagtail-altstreamfield
Version: 0.0.13
Summary: An alternative implementation of the Wagtail StreamField.
Home-page: https://github.com/didorothy/wagtail-altstreamfield
Author: David Dorothy
Author-email: didorothy@gmail.com
License: BSD-2-Clause
Platform: UNKNOWN
Classifier: Environment :: Web Environment
Classifier: Framework :: Django
Classifier: Framework :: Django :: 2.2
Classifier: Framework :: Django :: 3.2
Classifier: Intended Audience :: Developers
Classifier: License :: OSI Approved :: BSD License
Classifier: Operating System :: OS Independent
Classifier: Programming Language :: Python
Classifier: Programming Language :: Python :: 3
Classifier: Programming Language :: Python :: 3 :: Only
Classifier: Programming Language :: Python :: 3.6
Classifier: Programming Language :: Python :: 3.7
Classifier: Programming Language :: Python :: 3.8
Classifier: Topic :: Internet :: WWW/HTTP
Classifier: Topic :: Internet :: WWW/HTTP :: Dynamic Content
License-File: LICENSE
Requires-Dist: Django <3.3,>=2.2
Requires-Dist: wagtail <4.0,>=2.7
